LICENSE
MANIFEST.in
README.md
setup.py
src/core/allPoints.h
src/core/checks.h
src/core/insidePoints.h
src/core/intersectionPoints.h
src/core/polygonArea.h
src/core/quad_iou_tensors.cpp
src/core/quad_iou_tensors.cu
src/core/quad_iou_tensors_bind_cpu.cpp
src/core/quad_iou_tensors_bind_cuda.cpp
src/core/simpleIntersectCheck.h
src/core/sortPoints.h
src/core/utils.h
src/quad_iou/__init__.py
src/quad_iou/wrap.py
src/quad_iou.egg-info/PKG-INFO
src/quad_iou.egg-info/SOURCES.txt
src/quad_iou.egg-info/dependency_links.txt
src/quad_iou.egg-info/top_level.txt