Metadata-Version: 2.1
Name: quad_iou
Version: 0.2.0
Summary: Torch extension for calculating IoU(Intersection over Union) for quadrilaterals(MxN)
Home-page: https://github.com/Isalia20/quad-iou-torch
Author: Irakli Salia
Author-email: irakli.salia854@gmail.com
Requires-Python: >=3.9
License-File: LICENSE
